easy_subprocess/__init__.py
easy_subprocess/easy_subprocess.py
easy_subprocess-1.1.0.post2.dist-info/METADATA
easy_subprocess-1.1.0.post2.dist-info/WHEEL
easy_subprocess-1.1.0.post2.dist-info/RECORD
