Metadata-Version: 2.4
Name: easy-subprocess
Version: 1.1.0.post2
Summary: A higher level alternative to subprocess.Popen which also supports non-blocking reads
Project-URL: Homepage, https://github.com/pyhacks/easy-subprocess
Author-email: pyhacks <enginyildirim111@gmail.com>
Keywords: non-blocking,subprocess
Requires-Dist: psutil
